[{"_id": 1, "name": "Course #1", "duration": 90, "date_begin": "2023-04-01", "date_end": "2023-04-12", "description": "Course #1 description.", "lecturer": "Kristy Murray", "price": 40000}, {"_id": 2, "name": "Course #2", "duration": 30, "date_begin": "2023-05-30", "date_end": "2023-05-30", "description": "Course #2 description.", "lecturer": "Mr. Dale Rodriguez", "price": 20000}, {"_id": 3, "name": "Course #3", "duration": 60, "date_begin": "2023-03-27", "date_end": "2023-05-05", "description": "Course #3 description.", "lecturer": "Allison Bell", "price": 30000}, {"_id": 4, "name": "Course #4", "duration": 90, "date_begin": "2023-04-29", "date_end": "2023-05-23", "description": "Course #4 description.", "lecturer": "Jessica Foley", "price": 40000}, {"_id": 5, "name": "Course #5", "duration": 100, "date_begin": "2023-03-29", "date_end": "2023-05-23", "description": "Course #5 description.", "lecturer": "Rachel Joseph", "price": 30000}]